[
  {
    "stage": "step2b",
    "timestamp": "2026-01-08T15:21:41.553304",
    "input_pattern": "*_step2_sanitized_scope_v1.jsonl",
    "mapping_source": "approved",
    "outputs": [
      {
        "file": "data/scope_v3/SAMSUNG_step2_canonical_scope_v1.jsonl",
        "sha256": "e5b27ada55590947",
        "line_count": 32,
        "schema_version": "scope_v3_step2b_v1"
      },
      {
        "file": "data/scope_v3/db_over41_step2_canonical_scope_v1.jsonl",
        "sha256": "7ddd0013620817b7",
        "line_count": 31,
        "schema_version": "scope_v3_step2b_v1"
      },
      {
        "file": "data/scope_v3/db_under40_step2_canonical_scope_v1.jsonl",
        "sha256": "d4697627c0e8b534",
        "line_count": 31,
        "schema_version": "scope_v3_step2b_v1"
      },
      {
        "file": "data/scope_v3/hanwha_step2_canonical_scope_v1.jsonl",
        "sha256": "a88e29702f9d233b",
        "line_count": 33,
        "schema_version": "scope_v3_step2b_v1"
      },
      {
        "file": "data/scope_v3/heungkuk_step2_canonical_scope_v1.jsonl",
        "sha256": "a26a3b721c68fed9",
        "line_count": 36,
        "schema_version": "scope_v3_step2b_v1"
      },
      {
        "file": "data/scope_v3/hyundai_step2_canonical_scope_v1.jsonl",
        "sha256": "8ef434ca27383706",
        "line_count": 37,
        "schema_version": "scope_v3_step2b_v1"
      },
      {
        "file": "data/scope_v3/kb_step2_canonical_scope_v1.jsonl",
        "sha256": "8b1b0344e969e84e",
        "line_count": 43,
        "schema_version": "scope_v3_step2b_v1"
      },
      {
        "file": "data/scope_v3/lotte_female_step2_canonical_scope_v1.jsonl",
        "sha256": "c39ab93783c4ad51",
        "line_count": 30,
        "schema_version": "scope_v3_step2b_v1"
      },
      {
        "file": "data/scope_v3/lotte_male_step2_canonical_scope_v1.jsonl",
        "sha256": "d55024c3b750487b",
        "line_count": 30,
        "schema_version": "scope_v3_step2b_v1"
      },
      {
        "file": "data/scope_v3/meritz_step2_canonical_scope_v1.jsonl",
        "sha256": "1e4da200e9ec92db",
        "line_count": 37,
        "schema_version": "scope_v3_step2b_v1"
      }
    ],
    "metrics": {
      "total_entries": 340,
      "mapped": 278,
      "unmapped": 62,
      "pct_mapped": 81.8
    },
    "status": "success"
  },
  {
    "stage": "step2b",
    "timestamp": "2026-01-08T15:21:47.237415",
    "input_pattern": "*_step2_sanitized_scope_v1.jsonl",
    "mapping_source": "approved",
    "outputs": [
      {
        "file": "data/scope_v3/SAMSUNG_step2_canonical_scope_v1.jsonl",
        "sha256": "e5b27ada55590947",
        "line_count": 32,
        "schema_version": "scope_v3_step2b_v1"
      },
      {
        "file": "data/scope_v3/db_over41_step2_canonical_scope_v1.jsonl",
        "sha256": "7ddd0013620817b7",
        "line_count": 31,
        "schema_version": "scope_v3_step2b_v1"
      },
      {
        "file": "data/scope_v3/db_under40_step2_canonical_scope_v1.jsonl",
        "sha256": "d4697627c0e8b534",
        "line_count": 31,
        "schema_version": "scope_v3_step2b_v1"
      },
      {
        "file": "data/scope_v3/hanwha_step2_canonical_scope_v1.jsonl",
        "sha256": "a88e29702f9d233b",
        "line_count": 33,
        "schema_version": "scope_v3_step2b_v1"
      },
      {
        "file": "data/scope_v3/heungkuk_step2_canonical_scope_v1.jsonl",
        "sha256": "a26a3b721c68fed9",
        "line_count": 36,
        "schema_version": "scope_v3_step2b_v1"
      },
      {
        "file": "data/scope_v3/hyundai_step2_canonical_scope_v1.jsonl",
        "sha256": "8ef434ca27383706",
        "line_count": 37,
        "schema_version": "scope_v3_step2b_v1"
      },
      {
        "file": "data/scope_v3/kb_step2_canonical_scope_v1.jsonl",
        "sha256": "8b1b0344e969e84e",
        "line_count": 43,
        "schema_version": "scope_v3_step2b_v1"
      },
      {
        "file": "data/scope_v3/lotte_female_step2_canonical_scope_v1.jsonl",
        "sha256": "c39ab93783c4ad51",
        "line_count": 30,
        "schema_version": "scope_v3_step2b_v1"
      },
      {
        "file": "data/scope_v3/lotte_male_step2_canonical_scope_v1.jsonl",
        "sha256": "d55024c3b750487b",
        "line_count": 30,
        "schema_version": "scope_v3_step2b_v1"
      },
      {
        "file": "data/scope_v3/meritz_step2_canonical_scope_v1.jsonl",
        "sha256": "1e4da200e9ec92db",
        "line_count": 37,
        "schema_version": "scope_v3_step2b_v1"
      }
    ],
    "metrics": {
      "total_entries": 340,
      "mapped": 278,
      "unmapped": 62,
      "pct_mapped": 81.8
    },
    "status": "success"
  },
  {
    "stage": "step4",
    "timestamp": "2026-01-09T11:16:05.171730",
    "inputs": [
      "data/scope_v3/SAMSUNG_step3_evidence_enriched_v1_gated.jsonl",
      "data/scope_v3/db_over41_step3_evidence_enriched_v1_gated.jsonl",
      "data/scope_v3/db_under40_step3_evidence_enriched_v1_gated.jsonl",
      "data/scope_v3/hanwha_step3_evidence_enriched_v1_gated.jsonl",
      "data/scope_v3/heungkuk_step3_evidence_enriched_v1_gated.jsonl",
      "data/scope_v3/hyundai_step3_evidence_enriched_v1_gated.jsonl",
      "data/scope_v3/kb_step3_evidence_enriched_v1_gated.jsonl",
      "data/scope_v3/lotte_female_step3_evidence_enriched_v1_gated.jsonl",
      "data/scope_v3/lotte_male_step3_evidence_enriched_v1_gated.jsonl",
      "data/scope_v3/meritz_step3_evidence_enriched_v1_gated.jsonl"
    ],
    "outputs": [
      {
        "file": "data/compare_v1/compare_rows_v1.jsonl",
        "sha256": "64d6b3a26f4a6888",
        "line_count": 340,
        "schema_version": "v1"
      },
      {
        "file": "data/compare_v1/compare_tables_v1.jsonl",
        "sha256": "5907dac63def721f",
        "line_count": 1,
        "schema_version": "v1"
      }
    ],
    "status": "success"
  },
  {
    "stage": "step4",
    "timestamp": "2026-01-09T12:30:06.887514",
    "inputs": [
      "data/scope_v3/SAMSUNG_step3_evidence_enriched_v1_gated.jsonl",
      "data/scope_v3/db_over41_step3_evidence_enriched_v1_gated.jsonl",
      "data/scope_v3/db_under40_step3_evidence_enriched_v1_gated.jsonl",
      "data/scope_v3/hanwha_step3_evidence_enriched_v1_gated.jsonl",
      "data/scope_v3/heungkuk_step3_evidence_enriched_v1_gated.jsonl",
      "data/scope_v3/hyundai_step3_evidence_enriched_v1_gated.jsonl",
      "data/scope_v3/kb_step3_evidence_enriched_v1_gated.jsonl",
      "data/scope_v3/lotte_female_step3_evidence_enriched_v1_gated.jsonl",
      "data/scope_v3/lotte_male_step3_evidence_enriched_v1_gated.jsonl",
      "data/scope_v3/meritz_step3_evidence_enriched_v1_gated.jsonl"
    ],
    "outputs": [
      {
        "file": "data/compare_v1/compare_rows_v1.jsonl",
        "sha256": "b91b9f042f27596b",
        "line_count": 340,
        "schema_version": "v1"
      },
      {
        "file": "data/compare_v1/compare_tables_v1.jsonl",
        "sha256": "25b80bb705ba0621",
        "line_count": 1,
        "schema_version": "v1"
      }
    ],
    "status": "success"
  },
  {
    "stage": "step4",
    "timestamp": "2026-01-09T13:31:37.532423",
    "inputs": [
      "data/scope_v3/SAMSUNG_step3_evidence_enriched_v1_gated.jsonl",
      "data/scope_v3/db_over41_step3_evidence_enriched_v1_gated.jsonl",
      "data/scope_v3/db_under40_step3_evidence_enriched_v1_gated.jsonl",
      "data/scope_v3/hanwha_step3_evidence_enriched_v1_gated.jsonl",
      "data/scope_v3/heungkuk_step3_evidence_enriched_v1_gated.jsonl",
      "data/scope_v3/hyundai_step3_evidence_enriched_v1_gated.jsonl",
      "data/scope_v3/kb_step3_evidence_enriched_v1_gated.jsonl",
      "data/scope_v3/lotte_female_step3_evidence_enriched_v1_gated.jsonl",
      "data/scope_v3/lotte_male_step3_evidence_enriched_v1_gated.jsonl",
      "data/scope_v3/meritz_step3_evidence_enriched_v1_gated.jsonl"
    ],
    "outputs": [
      {
        "file": "data/compare_v1/compare_rows_v1.jsonl",
        "sha256": "6d528b2b3545419c",
        "line_count": 340,
        "schema_version": "v1"
      },
      {
        "file": "data/compare_v1/compare_tables_v1.jsonl",
        "sha256": "a3fe013f03e8dd9d",
        "line_count": 1,
        "schema_version": "v1"
      }
    ],
    "status": "success"
  },
  {
    "stage": "step4",
    "timestamp": "2026-01-12T09:51:27.279030",
    "inputs": [
      "data/scope_v3/SAMSUNG_step3_evidence_enriched_v1_gated.jsonl",
      "data/scope_v3/db_over41_step3_evidence_enriched_v1_gated.jsonl",
      "data/scope_v3/db_under40_step3_evidence_enriched_v1_gated.jsonl",
      "data/scope_v3/hanwha_step3_evidence_enriched_v1_gated.jsonl",
      "data/scope_v3/heungkuk_step3_evidence_enriched_v1_gated.jsonl",
      "data/scope_v3/hyundai_step3_evidence_enriched_v1_gated.jsonl",
      "data/scope_v3/kb_step3_evidence_enriched_v1_gated.jsonl",
      "data/scope_v3/lotte_female_step3_evidence_enriched_v1_gated.jsonl",
      "data/scope_v3/lotte_male_step3_evidence_enriched_v1_gated.jsonl",
      "data/scope_v3/meritz_step3_evidence_enriched_v1_gated.jsonl"
    ],
    "outputs": [
      {
        "file": "data/compare_v1/compare_rows_v1.jsonl",
        "sha256": "404551c89f44f1cc",
        "line_count": 340,
        "schema_version": "v1"
      },
      {
        "file": "data/compare_v1/compare_tables_v1.jsonl",
        "sha256": "12481c96b27bd01c",
        "line_count": 1,
        "schema_version": "v1"
      }
    ],
    "status": "success"
  },
  {
    "stage": "step4",
    "timestamp": "2026-01-12T09:52:01.425379",
    "inputs": [
      "data/scope_v3/SAMSUNG_step3_evidence_enriched_v1_gated.jsonl",
      "data/scope_v3/db_over41_step3_evidence_enriched_v1_gated.jsonl",
      "data/scope_v3/db_under40_step3_evidence_enriched_v1_gated.jsonl",
      "data/scope_v3/hanwha_step3_evidence_enriched_v1_gated.jsonl",
      "data/scope_v3/heungkuk_step3_evidence_enriched_v1_gated.jsonl",
      "data/scope_v3/hyundai_step3_evidence_enriched_v1_gated.jsonl",
      "data/scope_v3/kb_step3_evidence_enriched_v1_gated.jsonl",
      "data/scope_v3/lotte_female_step3_evidence_enriched_v1_gated.jsonl",
      "data/scope_v3/lotte_male_step3_evidence_enriched_v1_gated.jsonl",
      "data/scope_v3/meritz_step3_evidence_enriched_v1_gated.jsonl"
    ],
    "outputs": [
      {
        "file": "data/compare_v1/compare_rows_v1.jsonl",
        "sha256": "5ffd888b1463b393",
        "line_count": 340,
        "schema_version": "v1"
      },
      {
        "file": "data/compare_v1/compare_tables_v1.jsonl",
        "sha256": "5847043a90f49e5c",
        "line_count": 1,
        "schema_version": "v1"
      }
    ],
    "status": "success"
  }
]